lribeiro.cherrypy.authorizer.mongoengine-1.0.1-py3.4-nspkg.pth
lribeiro/cherrypy/authorizer/mongoengine/__init__.py
lribeiro/cherrypy/authorizer/mongoengine/models.py
lribeiro/cherrypy/authorizer/mongoengine/auth.py
lribeiro.cherrypy.authorizer.mongoengine-1.0.1.dist-info/WHEEL
lribeiro.cherrypy.authorizer.mongoengine-1.0.1.dist-info/top_level.txt
lribeiro.cherrypy.authorizer.mongoengine-1.0.1.dist-info/DESCRIPTION.rst
lribeiro.cherrypy.authorizer.mongoengine-1.0.1.dist-info/namespace_packages.txt
lribeiro.cherrypy.authorizer.mongoengine-1.0.1.dist-info/METADATA
lribeiro.cherrypy.authorizer.mongoengine-1.0.1.dist-info/metadata.json
lribeiro.cherrypy.authorizer.mongoengine-1.0.1.dist-info/RECORD
