Metadata-Version: 2.0
Name: lribeiro.cherrypy.authorizer.mongoengine
Version: 1.0.1
Summary: Basic user model, authenticator and authorizer for lribeiro.cherrypy.authorizer and mongoengine
Home-page: http://bitbucket.org/livioribeiro/cherrypy-authorizer-mongoengine
Author: Livio Ribeiro
Author-email: livioribeiro@outlook.com
License: BSD License
Keywords: authentication,authorization,access control,cherrypy,mongoengine
Platform: UNKNOWN
Classifier: Development Status :: 4 - Beta
Classifier: Environment :: Web Environment
Classifier: Framework :: CherryPy
Classifier: Intended Audience :: Developers
Classifier: License :: OSI Approved :: BSD License
Classifier: Operating System :: OS Independent
Classifier: Programming Language :: Python
Classifier: Programming Language :: Python :: 3
Classifier: Programming Language :: Python :: 3.3
Classifier: Topic :: Internet :: WWW/HTTP
Classifier: Topic :: Internet :: WWW/HTTP :: Dynamic Content
Classifier: Topic :: Internet :: WWW/HTTP :: Session
Requires-Dist: CherryPy
Requires-Dist: mongoengine
Requires-Dist: bcrypt
Requires-Dist: lribeiro.cherrypy.authorizer
